trust3_client/PluginAccessRequestEncryptor.py
trust3_client/VERSION
trust3_client/__init__.py
trust3_client/backend.py
trust3_client/client.py
trust3_client/core.py
trust3_client/encryption.py
trust3_client/exception.py
trust3_client/interceptor.py
trust3_client/interceptor_setup.py
trust3_client/langchain_callback.py
trust3_client/langchain_method_interceptor.py
trust3_client/langchain_streaming_interceptor.py
trust3_client/message.py
trust3_client/milvus_method_interceptor.py
trust3_client/model.py
trust3_client/opensearch_method_interceptor.py
trust3_client/snowflake_token_generator.py
trust3_client/util.py
trust3_client/posthog_events/__init__.py
trust3_client/posthog_events/events.py
trust3_client/posthog_events/metric_collector.py
trust3_client/posthog_events/posthog.py
trust3_client/trust3_common/VERSION
trust3_client/trust3_common/__init__.py
trust3_client/trust3_common/async_base_rest_http_client.py
trust3_client/trust3_common/async_http_transport.py
trust3_client/trust3_common/audit_spooler.py
trust3_client/trust3_common/config_utils.py
trust3_client/trust3_common/constants.py
trust3_client/trust3_common/encryption.py
trust3_client/trust3_common/file_utils.py
trust3_client/trust3_common/http_transport.py
trust3_client/trust3_common/lru_cache.py
trust3_client/trust3_common/paig_exception.py
trust3_client/trust3_common/rbac_manager.py
trust3_client/trust3_common/response.py
trust3_client-1.0.0.dist-info/METADATA
trust3_client-1.0.0.dist-info/WHEEL
trust3_client-1.0.0.dist-info/RECORD
