Metadata-Version: 2.4
Name: trust3-client
Version: 1.0.0
Summary: Python client library for integrating Trust3 AI governance and security features
Project-URL: Documentation, https://docs.trust3.ai
Author-email: Trust3 Team <support@trust3.ai>
License:                                  Apache License
Classifier: License :: Other/Proprietary License
Classifier: Operating System :: OS Independent
Classifier: Programming Language :: Python :: 3
Requires-Python: >=3.8.1
Requires-Dist: cryptography==41.0.4
Requires-Dist: posthog
Requires-Dist: pyjwt>=2.10.1
Requires-Dist: requests>=2.32.3
Requires-Dist: urllib3>=2.0.6
